aio_tg_bot/__init__.py
aio_tg_bot/__main__.py
aio_tg_bot/config.py
aio_tg_bot/version.py
aio_tg_bot/core/__init__.py
aio_tg_bot/core/exceptions.py
aio_tg_bot/etc/__init__.py
aio_tg_bot/etc/__main__.py
aio_tg_bot/etc/context_processors.py
aio_tg_bot/etc/utils.py
aio_tg_bot/etc/conf/__init__.py
aio_tg_bot/etc/conf/default_settings.py
aio_tg_bot/etc/conf/settings.py
aio_tg_bot/etc/database/__init__.py
aio_tg_bot/etc/database/callback_data_filter.py
aio_tg_bot/etc/database/exceptions.py
aio_tg_bot/etc/database/fields.py
aio_tg_bot/etc/database/model.py
aio_tg_bot/etc/database/models.py
aio_tg_bot/etc/database/state.py
aio_tg_bot/etc/database/users.py
aio_tg_bot/etc/database/validators.py
aio_tg_bot/etc/database/migrations/__init__.py
aio_tg_bot/etc/database/migrations/__main__.py
aio_tg_bot/etc/database/migrations/actions.py
aio_tg_bot/etc/database/migrations/auto.py
aio_tg_bot/etc/database/migrations/cli.py
aio_tg_bot/etc/database/migrations/compat.py
aio_tg_bot/etc/database/migrations/helper.py
aio_tg_bot/etc/database/migrations/logger.py
aio_tg_bot/etc/database/migrations/migrator.py
aio_tg_bot/etc/database/migrations/router.py
aio_tg_bot/etc/management/__init__.py
aio_tg_bot/etc/management/commands/__init__.py
aio_tg_bot/etc/management/commands/__main__.py
aio_tg_bot/etc/management/commands/makemigrations.py
aio_tg_bot/etc/management/commands/migrate.py
aio_tg_bot/etc/migrations/001_aio_tg_bot.py
aio_tg_bot/etc/migrations/002_aio_tg_bot.py
aio_tg_bot/etc/migrations/003_aio_tg_bot.py
aio_tg_bot/etc/migrations/004_aio_tg_bot.py
aio_tg_bot/etc/migrations/__init__.py
aio_tg_bot/etc/pay/__init__.py
aio_tg_bot/etc/pay/qiwi.py
aio_tg_bot/etc/pay/yoomoney.py
aio_tg_bot/etc/text/__init__.py
aio_tg_bot/etc/text/utils.py
aio_tg_bot/etc/text/keyboards/__init__.py
aio_tg_bot/etc/text/keyboards/mixin.py
aio_tg_bot/filters/__init__.py
aio_tg_bot/filters/__main__.py
aio_tg_bot/filters/callback_data.py
aio_tg_bot/filters/is_admin.py
aio_tg_bot/fsm_storage/__init__.py
aio_tg_bot-0.0.11.dist-info/METADATA
aio_tg_bot-0.0.11.dist-info/WHEEL
aio_tg_bot-0.0.11.dist-info/top_level.txt
aio_tg_bot-0.0.11.dist-info/RECORD
